bsmedit/__init__.py
bsmedit/__main__.py
bsmedit/mainframe.py
bsmedit/mainframexpm.py
bsmedit/version.py
bsmedit/bsm/__init__.py
bsmedit/bsm/bsm.h
bsmedit/bsm/bsmbackend.py
bsmedit/bsm/csim.py
bsmedit/bsm/debugtool.py
bsmedit/bsm/docstring.py
bsmedit/bsm/editor.py
bsmedit/bsm/graph.py
bsmedit/bsm/misctools.py
bsmedit/bsm/parsetab.py
bsmedit/bsm/pysim.py
bsmedit/bsm/shell.py
bsmedit/bsm/sim.py
bsmedit/bsm/simprocess.py
bsmedit/cparser/__init__.py
bsmedit/cparser/better_exchook.py
bsmedit/cparser/caching.py
bsmedit/cparser/cparser.py
bsmedit/cparser/cparser_utils.py
bsmedit/cparser/cwrapper.py
bsmedit/cparser/globalincludewrappers.py
bsmedit/cparser/goto.py
bsmedit/cparser/interpreter.py
bsmedit/cparser/py_demo_unparse.py
bsmedit/cparser/demos/interactive_test_parser.py
bsmedit/cparser/demos/test_interpreter.py
bsmedit/cparser/sortedcontainers/__init__.py
bsmedit/cparser/sortedcontainers/sorteddict.py
bsmedit/cparser/sortedcontainers/sortedlist.py
bsmedit/cparser/sortedcontainers/sortedset.py
bsmedit/cparser/tests/helpers_test.py
bsmedit/cparser/tests/test_funcptrdecl.py
bsmedit/cparser/tests/test_goto.py
bsmedit/cparser/tests/test_interpret_stmnt.py
bsmedit/cparser/tests/test_interpreter_helloworld.py
bsmedit/cparser/tests/test_parse_func.py
bsmedit/cparser/tests/test_parse_stmnt.py
bsmedit/cparser/tests/test_ptrtoptrdecl.py
bsmedit/cparser/tests/test_sdl_header.py
bsmedit/cparser/tests/test_simplevardecl.py
bsmedit/glsurface/__init__.py
bsmedit/glsurface/_simxpm.py
bsmedit/glsurface/glsurface.py
bsmedit/glsurface/gltest.py
examples/example.py
examples/start.py
examples/tb_dll/Verilog_VCD.py
examples/waves/setup.py
examples/waves/waves/__init__.py
examples/waves/waves/waves.py
examples/waves/waves/wavesxpm.py
bsmedit-3.2.14.dist-info/LICENSE
bsmedit-3.2.14.dist-info/METADATA
bsmedit-3.2.14.dist-info/WHEEL
bsmedit-3.2.14.dist-info/entry_points.txt
bsmedit-3.2.14.dist-info/top_level.txt
bsmedit-3.2.14.dist-info/RECORD
