Metadata-Version: 2.1
Name: bsmedit
Version: 3.2.14
Summary: C/C++/SystemC Visualizer
Author-email: Tianzhu Qiao <tq@feiyilin.com>
License: MIT License
Project-URL: Homepage, http://bsmedit.feiyilin.com
Classifier: Operating System :: OS Independent
Requires-Python: >=3.0
License-File: LICENSE
Requires-Dist: wxpython>=4.2.1
Requires-Dist: matplotlib>=3.8.1
Requires-Dist: numpy
Requires-Dist: click
Requires-Dist: PyOpenGL
Requires-Dist: PyOpenGL-accelerate
Requires-Dist: pandas
Requires-Dist: propgrid>=0.1.5
Requires-Dist: mplpanel>=0.1.8
Requires-Dist: aui2>=0.1.6
Requires-Dist: bsmutility>=0.2.3
